pexy/__init__.py
pexy/cli.py
pexy/command/__init__.py
pexy/command/access.py
pexy/command/collection.py
pexy/command/customer.py
pexy/command/order.py
pexy/command/product.py
pexy/command/store.py
pexy/exception/__init__.py
pexy/module/__init__.py
pexy/module/logger.py
pexy/module/shopify.py
pexy-0.9.6.dist-info/licenses/LICENSE.txt
pexy-0.9.6.dist-info/METADATA
pexy-0.9.6.dist-info/WHEEL
pexy-0.9.6.dist-info/entry_points.txt
pexy-0.9.6.dist-info/top_level.txt
pexy-0.9.6.dist-info/RECORD
