Metadata-Version: 2.4
Name: pexy
Version: 0.9.6
Summary: Shopify Store Swiss Knife.
Home-page: https://github.com/Clivern/Pexy/
Author: Clivern
Author-email: hello@clivern.com
License: MIT
Project-URL: Documentation, https://github.com/Clivern/Pexy/
Project-URL: Source, https://github.com/Clivern/Pexy/
Project-URL: Changelog, https://github.com/Clivern/Pexy/blob/main/CHANGELOG.rst
Project-URL: Tracker, https://github.com/Clivern/Pexy/issues
Project-URL: Download, https://pypi.org/project/Pexy/#files
Platform: any
Classifier: Development Status :: 5 - Production/Stable
Classifier: Programming Language :: Python
Classifier: License :: OSI Approved :: MIT License
License-File: LICENSE.txt
Requires-Dist: click<=8.3.0
Requires-Dist: requests<=2.32.5
Requires-Dist: rich<=14.2.0
Requires-Dist: importlib-metadata<=8.7.0; python_version < "3.8"
Dynamic: license-file
